hangman_tools/__init__.py
hangman_tools/hangman_regexp/.ruff_cache/.gitignore
hangman_tools/hangman_regexp/.ruff_cache/0.14.6/13712535917070145089
hangman_tools/hangman_regexp/.ruff_cache/0.14.6/17723850397826733104
hangman_tools/hangman_regexp/.ruff_cache/CACHEDIR.TAG
hangman_tools/hangman_regexp/__init__.py
hangman_tools/make_hangman_phrase/__init__.py
hangman_tools-0.1.7.dist-info/WHEEL
hangman_tools-0.1.7.dist-info/entry_points.txt
hangman_tools-0.1.7.dist-info/METADATA
hangman_tools-0.1.7.dist-info/RECORD
