Metadata-Version: 2.3
Name: hangman-tools
Version: 0.1.7
Summary: Tools for playing and running hangman-like word games
Requires-Dist: argparse>=1.4.0
Requires-Python: >=3.13
